{
  "project_info": {
    "project_number": "634989098033",
    "project_id": "ecoplate-e7860",
    "storage_bucket": "ecoplate-e7860.appspot.com"
  },
  "client": [
    {
      "client_info": {
        "mobilesdk_app_id": "1:634989098033:android:d873bbbde9bf46c2e25110",
        "android_client_info": {
          "package_name": "com.example.ecoplate"
        }
      },
      "oauth_client": [],
      "api_key": [
        {
          "current_key": "AIzaSyCjvwXqIpWJ0ALHh-z9c8wKUkaUUOzlGws"
        }
      ],
      "services": {
        "appinvite_service": {
          "other_platform_oauth_client": []
        }
      }
    }
  ],
  "configuration_version": "1"
}